uptrace/__init__.py
uptrace/client.py
uptrace/distro.py
uptrace/dsn.py
uptrace/id_generator.py
uptrace/logs.py
uptrace/metrics.py
uptrace/traces.py
uptrace/uptrace.py
uptrace/util.py
uptrace/version.py
uptrace-1.28.2.dist-info/LICENSE
uptrace-1.28.2.dist-info/METADATA
uptrace-1.28.2.dist-info/WHEEL
uptrace-1.28.2.dist-info/entry_points.txt
uptrace-1.28.2.dist-info/top_level.txt
uptrace-1.28.2.dist-info/RECORD
