Metadata-Version: 2.1
Name: uptrace
Version: 1.28.2
Summary: OpenTelemetry Python distribution for Uptrace
Home-page: https://uptrace.dev
Author: Uptrace.dev
Author-email: support@uptrace.dev
License: BSD
Platform: any
Classifier: Development Status :: 4 - Beta
Classifier: Intended Audience :: Developers
Classifier: License :: OSI Approved :: BSD License
Classifier: Programming Language :: Python
Classifier: Programming Language :: Python :: 3
Classifier: Programming Language :: Python :: 3.8
Classifier: Typing :: Typed
Requires-Python: >=3.8
License-File: LICENSE
